fchecker
