Metadata-Version: 2.1
Name: fchecker
Version: 0.15.5
Summary: fchecker is designed to provide cleaner useable check exceptions.
Home-page: https://github.com/IncognitoCoding/fchecker
Author: IncognitoCoding
License: MIT
Platform: any
Classifier: Development Status :: 4 - Beta
Classifier: Programming Language :: Python :: 3
Classifier: License :: OSI Approved :: MIT License
Classifier: Operating System :: POSIX :: Linux
Classifier: Operating System :: Microsoft :: Windows
Provides-Extra: testing
License-File: LICENSE
